vcf_handler/__init__.py
vcf_handler/__main__.py
vcf_handler/cli.py
vcf_handler/process.py
vcf_handler/utils/Variant.py
vcf_handler/utils/__init__.py
vcf_handler/utils/read_write.py
vcf_handler/utils/vep_helpers.py
gabry_vcf_handler-1.3.0.dist-info/WHEEL
gabry_vcf_handler-1.3.0.dist-info/METADATA
gabry_vcf_handler-1.3.0.dist-info/licenses/LICENSE
gabry_vcf_handler-1.3.0.dist-info/RECORD
