Metadata-Version: 2.1
Name: gabry-vcf-handler
Version: 1.3.0
Summary: VCF to .csv handler catered to specific desired fields
License: MIT
Author-email: Nick Gabry <n.t.gabry@gmail.com>
Requires-Python: >=3.9
Requires-Dist: cli-test-helpers>=3.4.0
Requires-Dist: click>=8.1.7
Requires-Dist: requests>=2.31.0
